motext/__init__.py
motext/scripts/__init__.py
motext/scripts/motext.py
motext-0.2.1.dist-info/LICENSE
motext-0.2.1.dist-info/METADATA
motext-0.2.1.dist-info/WHEEL
motext-0.2.1.dist-info/entry_points.txt
motext-0.2.1.dist-info/top_level.txt
motext-0.2.1.dist-info/RECORD
