Metadata-Version: 2.1
Name: motext
Version: 0.2.1
Summary: motext: The interface to the Multilingual Open Text (MOT) corpus
Home-page: https://github.com/bltlab/mot
Author: Constantine Lignos
Author-email: lignos@brandeis.edu
License: MIT
Classifier: Development Status :: 4 - Beta
Classifier: License :: OSI Approved :: MIT License
Classifier: Programming Language :: Python :: 3.8
Classifier: Programming Language :: Python :: 3.9
Classifier: Programming Language :: Python :: 3.10
Classifier: Topic :: Scientific/Engineering :: Artificial Intelligence
Requires-Python: >=3.8
License-File: LICENSE
Requires-Dist: click
